.gitignore
LICENSE
README.md
elba.png
setup.py
elba/__init__.py
elba/__main__.py
elba/autodiff.py
elba/config.py
elba/elba.py
elba/macro.py
elba/utils.py
elba.egg-info/PKG-INFO
elba.egg-info/SOURCES.txt
elba.egg-info/dependency_links.txt
elba.egg-info/entry_points.txt
elba.egg-info/not-zip-safe
elba.egg-info/requires.txt
elba.egg-info/top_level.txt
examples/example.py